asad_websearch_tool/__init__.py
asad_websearch_tool/tools.py
asad_websearch_tool-0.1.0.dist-info/licenses/LICENSE
asad_websearch_tool-0.1.0.dist-info/METADATA
asad_websearch_tool-0.1.0.dist-info/WHEEL
asad_websearch_tool-0.1.0.dist-info/top_level.txt
asad_websearch_tool-0.1.0.dist-info/RECORD
